LICENSE.txt
README.txt
setup.cfg
setup.py
docs/CONTRIBUTORS.txt
docs/HISTORY.txt
medialog/__init__.py
medialog.emailfield.egg-info/PKG-INFO
medialog.emailfield.egg-info/SOURCES.txt
medialog.emailfield.egg-info/dependency_links.txt
medialog.emailfield.egg-info/entry_points.txt
medialog.emailfield.egg-info/namespace_packages.txt
medialog.emailfield.egg-info/not-zip-safe
medialog.emailfield.egg-info/requires.txt
medialog.emailfield.egg-info/top_level.txt
medialog/emailfield/__init__.py
medialog/emailfield/config.py
medialog/emailfield/configure.zcml
medialog/emailfield/field.py
medialog/emailfield/interfaces.py
medialog/emailfield/content/__init__.py
medialog/emailfield/content/configure.zcml
medialog/emailfield/content/email.py
medialog/emailfield/profiles/default/metadata.xml
medialog/emailfield/profiles/test/emailwidget_marker.txt
medialog/emailfield/profiles/test/factorytool.xml
medialog/emailfield/profiles/test/types.xml
medialog/emailfield/profiles/test/types/Email.xml
medialog/emailfield/tests/__init__.py
medialog/emailfield/tests/base.py
medialog/emailfield/tests/test_emailfield.py