Metadata-Version: 1.0
Name: medialog.emailfield
Version: 0.1
Summary: Archetypes Widget dealing with email.
Home-page: http://medialog.no
Author: Espen Moe-Nilssen
Author-email: espen@medialog.no
License: GPL
Keywords: plone archetypes field email
Platform: UNKNOWN
Classifier: Programming Language :: Python
Classifier: Topic :: Software Development :: Libraries :: Python Modules
